{"cameraMode":{"drawMode":0,"name":"Shaded","section":"Shading Mode"},"sceneLighting":true,"audioPlay":false,"sceneViewState":{"m_AlwaysRefresh":false,"showFog":true,"showSkybox":true,"showFlares":true,"showImageEffects":true,"showParticleSystems":true,"showVisualEffectGraphs":true,"m_FxEnabled":true},"in2DMode":false,"pivot":{"x":14.066144943237305,"y":-4.676806926727295,"z":-2.5940239429473879},"rotation":{"x":-0.06928285211324692,"y":-0.8989645838737488,"z":0.1541345715522766,"w":-0.4040347635746002},"size":12.957629203796387,"orthographic":false}